kiarina/llm/__init__.py
kiarina/llm/py.typed
kiarina/llm/app_context/__init__.py
kiarina/llm/app_context/_settings.py
kiarina/llm/app_context/_helpers/__init__.py
kiarina/llm/app_context/_helpers/get_app_context.py
kiarina/llm/app_context/_models/__init__.py
kiarina/llm/app_context/_models/app_context.py
kiarina/llm/app_context/_types/__init__.py
kiarina/llm/app_context/_types/fs_name.py
kiarina/llm/run_context/__init__.py
kiarina/llm/run_context/_settings.py
kiarina/llm/run_context/_helpers/__init__.py
kiarina/llm/run_context/_helpers/create_run_context.py
kiarina/llm/run_context/_schemas/__init__.py
kiarina/llm/run_context/_schemas/run_context.py
kiarina/llm/run_context/_types/__init__.py
kiarina/llm/run_context/_types/id_str.py
kiarina_llm-1.35.0.dist-info/METADATA
kiarina_llm-1.35.0.dist-info/WHEEL
kiarina_llm-1.35.0.dist-info/RECORD
